{
  "downloaded_at": "2026-06-25T10:20:30.016150+00:00",
  "source": "Apache Jira REST API v2",
  "issue_key": "YARN-5990",
  "issue_url": "https://issues.apache.org/jira/rest/api/2/issue/YARN-5990?fields=id%2Ckey%2Csummary%2Cdescription%2Cparent%2Cvotes%2Ccomment%2Cattachment%2Cissuetype%2Cstatus%2Cpriority%2Cresolution%2Clabels%2Ccomponents%2Ccreated%2Cupdated%2Cissuelinks%2Csubtasks",
  "requested_fields": [
    "id",
    "key",
    "summary",
    "description",
    "parent",
    "votes",
    "comment",
    "attachment",
    "issuetype",
    "status",
    "priority",
    "resolution",
    "labels",
    "components",
    "created",
    "updated",
    "issuelinks",
    "subtasks"
  ],
  "issue_response": {
    "expand": "renderedFields,names,schema,operations,editmeta,changelog,versionedRepresentations",
    "id": "13027120",
    "self": "https://issues.apache.org/jira/rest/api/2/issue/13027120",
    "key": "YARN-5990",
    "fields": {
      "summary": "[Umbrella] Follow-up (phase-2) FairScheduler preemption improvements",
      "issuetype": {
        "self": "https://issues.apache.org/jira/rest/api/2/issuetype/1",
        "id": "1",
        "description": "A problem which impairs or prevents the functions of the product.",
        "iconUrl": "https://issues.apache.org/jira/secure/viewavatar?size=xsmall&avatarId=21133&avatarType=issuetype",
        "name": "Bug",
        "subtask": false,
        "avatarId": 21133
      },
      "components": [],
      "subtasks": [
        {
          "id": "13017834",
          "key": "YARN-5830",
          "self": "https://issues.apache.org/jira/rest/api/2/issue/13017834",
          "fields": {
            "summary": "FairScheduler: Avoid preempting AM containers",
            "status": {
              "self": "https://issues.apache.org/jira/rest/api/2/status/5",
              "description": "A resolution has been taken, and it is awaiting verification by reporter. From here issues are either reopened, or are closed.",
              "iconUrl": "https://issues.apache.org/jira/images/icons/statuses/resolved.png",
              "name": "Resolved",
              "id": "5",
              "statusCategory": {
                "self": "https://issues.apache.org/jira/rest/api/2/statuscategory/3",
                "id": 3,
                "key": "done",
                "colorName": "green",
                "name": "Done"
              }
            },
            "priority": {
              "self": "https://issues.apache.org/jira/rest/api/2/priority/3",
              "iconUrl": "https://issues.apache.org/jira/images/icons/priorities/major.svg",
              "name": "Major",
              "id": "3"
            },
            "issuetype": {
              "self": "https://issues.apache.org/jira/rest/api/2/issuetype/7",
              "id": "7",
              "description": "The sub-task of the issue",
              "iconUrl": "https://issues.apache.org/jira/secure/viewavatar?size=xsmall&avatarId=21146&avatarType=issuetype",
              "name": "Sub-task",
              "subtask": true,
              "avatarId": 21146
            }
          }
        },
        {
          "id": "13017850",
          "key": "YARN-5831",
          "self": "https://issues.apache.org/jira/rest/api/2/issue/13017850",
          "fields": {
            "summary": "Propagate allowPreemptionFrom flag all the way down to the app",
            "status": {
              "self": "https://issues.apache.org/jira/rest/api/2/status/5",
              "description": "A resolution has been taken, and it is awaiting verification by reporter. From here issues are either reopened, or are closed.",
              "iconUrl": "https://issues.apache.org/jira/images/icons/statuses/resolved.png",
              "name": "Resolved",
              "id": "5",
              "statusCategory": {
                "self": "https://issues.apache.org/jira/rest/api/2/statuscategory/3",
                "id": 3,
                "key": "done",
                "colorName": "green",
                "name": "Done"
              }
            },
            "priority": {
              "self": "https://issues.apache.org/jira/rest/api/2/priority/3",
              "iconUrl": "https://issues.apache.org/jira/images/icons/priorities/major.svg",
              "name": "Major",
              "id": "3"
            },
            "issuetype": {
              "self": "https://issues.apache.org/jira/rest/api/2/issuetype/7",
              "id": "7",
              "description": "The sub-task of the issue",
              "iconUrl": "https://issues.apache.org/jira/secure/viewavatar?size=xsmall&avatarId=21146&avatarType=issuetype",
              "name": "Sub-task",
              "subtask": true,
              "avatarId": 21146
            }
          }
        },
        {
          "id": "13021296",
          "key": "YARN-5893",
          "self": "https://issues.apache.org/jira/rest/api/2/issue/13021296",
          "fields": {
            "summary": "Experiment with using PriorityQueue for storing starved applications",
            "status": {
              "self": "https://issues.apache.org/jira/rest/api/2/status/5",
              "description": "A resolution has been taken, and it is awaiting verification by reporter. From here issues are either reopened, or are closed.",
              "iconUrl": "https://issues.apache.org/jira/images/icons/statuses/resolved.png",
              "name": "Resolved",
              "id": "5",
              "statusCategory": {
                "self": "https://issues.apache.org/jira/rest/api/2/statuscategory/3",
                "id": 3,
                "key": "done",
                "colorName": "green",
                "name": "Done"
              }
            },
            "priority": {
              "self": "https://issues.apache.org/jira/rest/api/2/priority/3",
              "iconUrl": "https://issues.apache.org/jira/images/icons/priorities/major.svg",
              "name": "Major",
              "id": "3"
            },
            "issuetype": {
              "self": "https://issues.apache.org/jira/rest/api/2/issuetype/7",
              "id": "7",
              "description": "The sub-task of the issue",
              "iconUrl": "https://issues.apache.org/jira/secure/viewavatar?size=xsmall&avatarId=21146&avatarType=issuetype",
              "name": "Sub-task",
              "subtask": true,
              "avatarId": 21146
            }
          }
        },
        {
          "id": "13041452",
          "key": "YARN-6163",
          "self": "https://issues.apache.org/jira/rest/api/2/issue/13041452",
          "fields": {
            "summary": "FS Preemption is a trickle for severely starved applications",
            "status": {
              "self": "https://issues.apache.org/jira/rest/api/2/status/5",
              "description": "A resolution has been taken, and it is awaiting verification by reporter. From here issues are either reopened, or are closed.",
              "iconUrl": "https://issues.apache.org/jira/images/icons/statuses/resolved.png",
              "name": "Resolved",
              "id": "5",
              "statusCategory": {
                "self": "https://issues.apache.org/jira/rest/api/2/statuscategory/3",
                "id": 3,
                "key": "done",
                "colorName": "green",
                "name": "Done"
              }
            },
            "priority": {
              "self": "https://issues.apache.org/jira/rest/api/2/priority/3",
              "iconUrl": "https://issues.apache.org/jira/images/icons/priorities/major.svg",
              "name": "Major",
              "id": "3"
            },
            "issuetype": {
              "self": "https://issues.apache.org/jira/rest/api/2/issuetype/7",
              "id": "7",
              "description": "The sub-task of the issue",
              "iconUrl": "https://issues.apache.org/jira/secure/viewavatar?size=xsmall&avatarId=21146&avatarType=issuetype",
              "name": "Sub-task",
              "subtask": true,
              "avatarId": 21146
            }
          }
        },
        {
          "id": "13043086",
          "key": "YARN-6193",
          "self": "https://issues.apache.org/jira/rest/api/2/issue/13043086",
          "fields": {
            "summary": "FairScheduler might not trigger preemption when using DRF",
            "status": {
              "self": "https://issues.apache.org/jira/rest/api/2/status/5",
              "description": "A resolution has been taken, and it is awaiting verification by reporter. From here issues are either reopened, or are closed.",
              "iconUrl": "https://issues.apache.org/jira/images/icons/statuses/resolved.png",
              "name": "Resolved",
              "id": "5",
              "statusCategory": {
                "self": "https://issues.apache.org/jira/rest/api/2/statuscategory/3",
                "id": 3,
                "key": "done",
                "colorName": "green",
                "name": "Done"
              }
            },
            "priority": {
              "self": "https://issues.apache.org/jira/rest/api/2/priority/3",
              "iconUrl": "https://issues.apache.org/jira/images/icons/priorities/major.svg",
              "name": "Major",
              "id": "3"
            },
            "issuetype": {
              "self": "https://issues.apache.org/jira/rest/api/2/issuetype/7",
              "id": "7",
              "description": "The sub-task of the issue",
              "iconUrl": "https://issues.apache.org/jira/secure/viewavatar?size=xsmall&avatarId=21146&avatarType=issuetype",
              "name": "Sub-task",
              "subtask": true,
              "avatarId": 21146
            }
          }
        },
        {
          "id": "13016246",
          "key": "YARN-5798",
          "self": "https://issues.apache.org/jira/rest/api/2/issue/13016246",
          "fields": {
            "summary": "Set UncaughtExceptionHandler for all FairScheduler threads",
            "status": {
              "self": "https://issues.apache.org/jira/rest/api/2/status/5",
              "description": "A resolution has been taken, and it is awaiting verification by reporter. From here issues are either reopened, or are closed.",
              "iconUrl": "https://issues.apache.org/jira/images/icons/statuses/resolved.png",
              "name": "Resolved",
              "id": "5",
              "statusCategory": {
                "self": "https://issues.apache.org/jira/rest/api/2/statuscategory/3",
                "id": 3,
                "key": "done",
                "colorName": "green",
                "name": "Done"
              }
            },
            "priority": {
              "self": "https://issues.apache.org/jira/rest/api/2/priority/3",
              "iconUrl": "https://issues.apache.org/jira/images/icons/priorities/major.svg",
              "name": "Major",
              "id": "3"
            },
            "issuetype": {
              "self": "https://issues.apache.org/jira/rest/api/2/issuetype/7",
              "id": "7",
              "description": "The sub-task of the issue",
              "iconUrl": "https://issues.apache.org/jira/secure/viewavatar?size=xsmall&avatarId=21146&avatarType=issuetype",
              "name": "Sub-task",
              "subtask": true,
              "avatarId": 21146
            }
          }
        },
        {
          "id": "13017517",
          "key": "YARN-5824",
          "self": "https://issues.apache.org/jira/rest/api/2/issue/13017517",
          "fields": {
            "summary": "Verify app starvation under custom preemption thresholds and timeouts",
            "status": {
              "self": "https://issues.apache.org/jira/rest/api/2/status/1",
              "description": "The issue is open and ready for the assignee to start work on it.",
              "iconUrl": "https://issues.apache.org/jira/images/icons/statuses/open.png",
              "name": "Open",
              "id": "1",
              "statusCategory": {
                "self": "https://issues.apache.org/jira/rest/api/2/statuscategory/2",
                "id": 2,
                "key": "new",
                "colorName": "blue-gray",
                "name": "To Do"
              }
            },
            "priority": {
              "self": "https://issues.apache.org/jira/rest/api/2/priority/3",
              "iconUrl": "https://issues.apache.org/jira/images/icons/priorities/major.svg",
              "name": "Major",
              "id": "3"
            },
            "issuetype": {
              "self": "https://issues.apache.org/jira/rest/api/2/issuetype/7",
              "id": "7",
              "description": "The sub-task of the issue",
              "iconUrl": "https://issues.apache.org/jira/secure/viewavatar?size=xsmall&avatarId=21146&avatarType=issuetype",
              "name": "Sub-task",
              "subtask": true,
              "avatarId": 21146
            }
          }
        },
        {
          "id": "13017854",
          "key": "YARN-5832",
          "self": "https://issues.apache.org/jira/rest/api/2/issue/13017854",
          "fields": {
            "summary": "Preemption should consider more resource-requests of a starved app if the initial set can not be satisfied",
            "status": {
              "self": "https://issues.apache.org/jira/rest/api/2/status/1",
              "description": "The issue is open and ready for the assignee to start work on it.",
              "iconUrl": "https://issues.apache.org/jira/images/icons/statuses/open.png",
              "name": "Open",
              "id": "1",
              "statusCategory": {
                "self": "https://issues.apache.org/jira/rest/api/2/statuscategory/2",
                "id": 2,
                "key": "new",
                "colorName": "blue-gray",
                "name": "To Do"
              }
            },
            "priority": {
              "self": "https://issues.apache.org/jira/rest/api/2/priority/3",
              "iconUrl": "https://issues.apache.org/jira/images/icons/priorities/major.svg",
              "name": "Major",
              "id": "3"
            },
            "issuetype": {
              "self": "https://issues.apache.org/jira/rest/api/2/issuetype/7",
              "id": "7",
              "description": "The sub-task of the issue",
              "iconUrl": "https://issues.apache.org/jira/secure/viewavatar?size=xsmall&avatarId=21146&avatarType=issuetype",
              "name": "Sub-task",
              "subtask": true,
              "avatarId": 21146
            }
          }
        },
        {
          "id": "13042241",
          "key": "YARN-6176",
          "self": "https://issues.apache.org/jira/rest/api/2/issue/13042241",
          "fields": {
            "summary": "Test whether FS preemption consider child queues over fair share if the parent is under fair share",
            "status": {
              "self": "https://issues.apache.org/jira/rest/api/2/status/5",
              "description": "A resolution has been taken, and it is awaiting verification by reporter. From here issues are either reopened, or are closed.",
              "iconUrl": "https://issues.apache.org/jira/images/icons/statuses/resolved.png",
              "name": "Resolved",
              "id": "5",
              "statusCategory": {
                "self": "https://issues.apache.org/jira/rest/api/2/statuscategory/3",
                "id": 3,
                "key": "done",
                "colorName": "green",
                "name": "Done"
              }
            },
            "priority": {
              "self": "https://issues.apache.org/jira/rest/api/2/priority/3",
              "iconUrl": "https://issues.apache.org/jira/images/icons/priorities/major.svg",
              "name": "Major",
              "id": "3"
            },
            "issuetype": {
              "self": "https://issues.apache.org/jira/rest/api/2/issuetype/7",
              "id": "7",
              "description": "The sub-task of the issue",
              "iconUrl": "https://issues.apache.org/jira/secure/viewavatar?size=xsmall&avatarId=21146&avatarType=issuetype",
              "name": "Sub-task",
              "subtask": true,
              "avatarId": 21146
            }
          }
        },
        {
          "id": "13045193",
          "key": "YARN-6215",
          "self": "https://issues.apache.org/jira/rest/api/2/issue/13045193",
          "fields": {
            "summary": "FairScheduler preemption and update should not run concurrently",
            "status": {
              "self": "https://issues.apache.org/jira/rest/api/2/status/5",
              "description": "A resolution has been taken, and it is awaiting verification by reporter. From here issues are either reopened, or are closed.",
              "iconUrl": "https://issues.apache.org/jira/images/icons/statuses/resolved.png",
              "name": "Resolved",
              "id": "5",
              "statusCategory": {
                "self": "https://issues.apache.org/jira/rest/api/2/statuscategory/3",
                "id": 3,
                "key": "done",
                "colorName": "green",
                "name": "Done"
              }
            },
            "priority": {
              "self": "https://issues.apache.org/jira/rest/api/2/priority/3",
              "iconUrl": "https://issues.apache.org/jira/images/icons/priorities/major.svg",
              "name": "Major",
              "id": "3"
            },
            "issuetype": {
              "self": "https://issues.apache.org/jira/rest/api/2/issuetype/7",
              "id": "7",
              "description": "The sub-task of the issue",
              "iconUrl": "https://issues.apache.org/jira/secure/viewavatar?size=xsmall&avatarId=21146&avatarType=issuetype",
              "name": "Sub-task",
              "subtask": true,
              "avatarId": 21146
            }
          }
        },
        {
          "id": "12662739",
          "key": "YARN-1047",
          "self": "https://issues.apache.org/jira/rest/api/2/issue/12662739",
          "fields": {
            "summary": "Expose # of pre-emptions as a queue counter",
            "status": {
              "self": "https://issues.apache.org/jira/rest/api/2/status/5",
              "description": "A resolution has been taken, and it is awaiting verification by reporter. From here issues are either reopened, or are closed.",
              "iconUrl": "https://issues.apache.org/jira/images/icons/statuses/resolved.png",
              "name": "Resolved",
              "id": "5",
              "statusCategory": {
                "self": "https://issues.apache.org/jira/rest/api/2/statuscategory/3",
                "id": 3,
                "key": "done",
                "colorName": "green",
                "name": "Done"
              }
            },
            "priority": {
              "self": "https://issues.apache.org/jira/rest/api/2/priority/3",
              "iconUrl": "https://issues.apache.org/jira/images/icons/priorities/major.svg",
              "name": "Major",
              "id": "3"
            },
            "issuetype": {
              "self": "https://issues.apache.org/jira/rest/api/2/issuetype/7",
              "id": "7",
              "description": "The sub-task of the issue",
              "iconUrl": "https://issues.apache.org/jira/secure/viewavatar?size=xsmall&avatarId=21146&avatarType=issuetype",
              "name": "Sub-task",
              "subtask": true,
              "avatarId": 21146
            }
          }
        },
        {
          "id": "13046781",
          "key": "YARN-6246",
          "self": "https://issues.apache.org/jira/rest/api/2/issue/13046781",
          "fields": {
            "summary": "Identifying starved apps does not need the scheduler writelock",
            "status": {
              "self": "https://issues.apache.org/jira/rest/api/2/status/5",
              "description": "A resolution has been taken, and it is awaiting verification by reporter. From here issues are either reopened, or are closed.",
              "iconUrl": "https://issues.apache.org/jira/images/icons/statuses/resolved.png",
              "name": "Resolved",
              "id": "5",
              "statusCategory": {
                "self": "https://issues.apache.org/jira/rest/api/2/statuscategory/3",
                "id": 3,
                "key": "done",
                "colorName": "green",
                "name": "Done"
              }
            },
            "priority": {
              "self": "https://issues.apache.org/jira/rest/api/2/priority/3",
              "iconUrl": "https://issues.apache.org/jira/images/icons/priorities/major.svg",
              "name": "Major",
              "id": "3"
            },
            "issuetype": {
              "self": "https://issues.apache.org/jira/rest/api/2/issuetype/7",
              "id": "7",
              "description": "The sub-task of the issue",
              "iconUrl": "https://issues.apache.org/jira/secure/viewavatar?size=xsmall&avatarId=21146&avatarType=issuetype",
              "name": "Sub-task",
              "subtask": true,
              "avatarId": 21146
            }
          }
        },
        {
          "id": "13049002",
          "key": "YARN-6298",
          "self": "https://issues.apache.org/jira/rest/api/2/issue/13049002",
          "fields": {
            "summary": "Metric preemptCall is not used in new preemption",
            "status": {
              "self": "https://issues.apache.org/jira/rest/api/2/status/5",
              "description": "A resolution has been taken, and it is awaiting verification by reporter. From here issues are either reopened, or are closed.",
              "iconUrl": "https://issues.apache.org/jira/images/icons/statuses/resolved.png",
              "name": "Resolved",
              "id": "5",
              "statusCategory": {
                "self": "https://issues.apache.org/jira/rest/api/2/statuscategory/3",
                "id": 3,
                "key": "done",
                "colorName": "green",
                "name": "Done"
              }
            },
            "priority": {
              "self": "https://issues.apache.org/jira/rest/api/2/priority/1",
              "iconUrl": "https://issues.apache.org/jira/images/icons/priorities/blocker.svg",
              "name": "Blocker",
              "id": "1"
            },
            "issuetype": {
              "self": "https://issues.apache.org/jira/rest/api/2/issuetype/7",
              "id": "7",
              "description": "The sub-task of the issue",
              "iconUrl": "https://issues.apache.org/jira/secure/viewavatar?size=xsmall&avatarId=21146&avatarType=issuetype",
              "name": "Sub-task",
              "subtask": true,
              "avatarId": 21146
            }
          }
        },
        {
          "id": "13061319",
          "key": "YARN-6432",
          "self": "https://issues.apache.org/jira/rest/api/2/issue/13061319",
          "fields": {
            "summary": "FairScheduler: Reserve preempted resources for corresponding applications",
            "status": {
              "self": "https://issues.apache.org/jira/rest/api/2/status/5",
              "description": "A resolution has been taken, and it is awaiting verification by reporter. From here issues are either reopened, or are closed.",
              "iconUrl": "https://issues.apache.org/jira/images/icons/statuses/resolved.png",
              "name": "Resolved",
              "id": "5",
              "statusCategory": {
                "self": "https://issues.apache.org/jira/rest/api/2/statuscategory/3",
                "id": 3,
                "key": "done",
                "colorName": "green",
                "name": "Done"
              }
            },
            "priority": {
              "self": "https://issues.apache.org/jira/rest/api/2/priority/3",
              "iconUrl": "https://issues.apache.org/jira/images/icons/priorities/major.svg",
              "name": "Major",
              "id": "3"
            },
            "issuetype": {
              "self": "https://issues.apache.org/jira/rest/api/2/issuetype/7",
              "id": "7",
              "description": "The sub-task of the issue",
              "iconUrl": "https://issues.apache.org/jira/secure/viewavatar?size=xsmall&avatarId=21146&avatarType=issuetype",
              "name": "Sub-task",
              "subtask": true,
              "avatarId": 21146
            }
          }
        },
        {
          "id": "13213542",
          "key": "YARN-9277",
          "self": "https://issues.apache.org/jira/rest/api/2/issue/13213542",
          "fields": {
            "summary": "Add more restrictions In FairScheduler Preemption ",
            "status": {
              "self": "https://issues.apache.org/jira/rest/api/2/status/10002",
              "description": "A patch for this issue has been uploaded to JIRA by a contributor.",
              "iconUrl": "https://issues.apache.org/jira/images/icons/statuses/document.png",
              "name": "Patch Available",
              "id": "10002",
              "statusCategory": {
                "self": "https://issues.apache.org/jira/rest/api/2/statuscategory/4",
                "id": 4,
                "key": "indeterminate",
                "colorName": "yellow",
                "name": "In Progress"
              }
            },
            "priority": {
              "self": "https://issues.apache.org/jira/rest/api/2/priority/3",
              "iconUrl": "https://issues.apache.org/jira/images/icons/priorities/major.svg",
              "name": "Major",
              "id": "3"
            },
            "issuetype": {
              "self": "https://issues.apache.org/jira/rest/api/2/issuetype/7",
              "id": "7",
              "description": "The sub-task of the issue",
              "iconUrl": "https://issues.apache.org/jira/secure/viewavatar?size=xsmall&avatarId=21146&avatarType=issuetype",
              "name": "Sub-task",
              "subtask": true,
              "avatarId": 21146
            }
          }
        },
        {
          "id": "13213574",
          "key": "YARN-9278",
          "self": "https://issues.apache.org/jira/rest/api/2/issue/13213574",
          "fields": {
            "summary": "Shuffle nodes when selecting to be preempted nodes",
            "status": {
              "self": "https://issues.apache.org/jira/rest/api/2/status/10002",
              "description": "A patch for this issue has been uploaded to JIRA by a contributor.",
              "iconUrl": "https://issues.apache.org/jira/images/icons/statuses/document.png",
              "name": "Patch Available",
              "id": "10002",
              "statusCategory": {
                "self": "https://issues.apache.org/jira/rest/api/2/statuscategory/4",
                "id": 4,
                "key": "indeterminate",
                "colorName": "yellow",
                "name": "In Progress"
              }
            },
            "priority": {
              "self": "https://issues.apache.org/jira/rest/api/2/priority/3",
              "iconUrl": "https://issues.apache.org/jira/images/icons/priorities/major.svg",
              "name": "Major",
              "id": "3"
            },
            "issuetype": {
              "self": "https://issues.apache.org/jira/rest/api/2/issuetype/7",
              "id": "7",
              "description": "The sub-task of the issue",
              "iconUrl": "https://issues.apache.org/jira/secure/viewavatar?size=xsmall&avatarId=21146&avatarType=issuetype",
              "name": "Sub-task",
              "subtask": true,
              "avatarId": 21146
            }
          }
        },
        {
          "id": "13180873",
          "key": "YARN-8707",
          "self": "https://issues.apache.org/jira/rest/api/2/issue/13180873",
          "fields": {
            "summary": "It's not reasonable to decide whether app is starved by fairShare",
            "status": {
              "self": "https://issues.apache.org/jira/rest/api/2/status/10002",
              "description": "A patch for this issue has been uploaded to JIRA by a contributor.",
              "iconUrl": "https://issues.apache.org/jira/images/icons/statuses/document.png",
              "name": "Patch Available",
              "id": "10002",
              "statusCategory": {
                "self": "https://issues.apache.org/jira/rest/api/2/statuscategory/4",
                "id": 4,
                "key": "indeterminate",
                "colorName": "yellow",
                "name": "In Progress"
              }
            },
            "priority": {
              "self": "https://issues.apache.org/jira/rest/api/2/priority/4",
              "iconUrl": "https://issues.apache.org/jira/images/icons/priorities/minor.svg",
              "name": "Minor",
              "id": "4"
            },
            "issuetype": {
              "self": "https://issues.apache.org/jira/rest/api/2/issuetype/7",
              "id": "7",
              "description": "The sub-task of the issue",
              "iconUrl": "https://issues.apache.org/jira/secure/viewavatar?size=xsmall&avatarId=21146&avatarType=issuetype",
              "name": "Sub-task",
              "subtask": true,
              "avatarId": 21146
            }
          }
        },
        {
          "id": "13178591",
          "key": "YARN-8655",
          "self": "https://issues.apache.org/jira/rest/api/2/issue/13178591",
          "fields": {
            "summary": "FairScheduler: FSStarvedApps is not thread safe",
            "status": {
              "self": "https://issues.apache.org/jira/rest/api/2/status/10002",
              "description": "A patch for this issue has been uploaded to JIRA by a contributor.",
              "iconUrl": "https://issues.apache.org/jira/images/icons/statuses/document.png",
              "name": "Patch Available",
              "id": "10002",
              "statusCategory": {
                "self": "https://issues.apache.org/jira/rest/api/2/statuscategory/4",
                "id": 4,
                "key": "indeterminate",
                "colorName": "yellow",
                "name": "In Progress"
              }
            },
            "priority": {
              "self": "https://issues.apache.org/jira/rest/api/2/priority/3",
              "iconUrl": "https://issues.apache.org/jira/images/icons/priorities/major.svg",
              "name": "Major",
              "id": "3"
            },
            "issuetype": {
              "self": "https://issues.apache.org/jira/rest/api/2/issuetype/7",
              "id": "7",
              "description": "The sub-task of the issue",
              "iconUrl": "https://issues.apache.org/jira/secure/viewavatar?size=xsmall&avatarId=21146&avatarType=issuetype",
              "name": "Sub-task",
              "subtask": true,
              "avatarId": 21146
            }
          }
        }
      ],
      "created": "2016-12-09T22:25:48.555+0000",
      "description": "YARN-4752 overhauled FS preemption. This JIRA is to track follow-up minor improvements discussed in the design doc on YARN-4752. \n\nThe reason for creating this is primarily for better release notes around YARN-4752. ",
      "priority": {
        "self": "https://issues.apache.org/jira/rest/api/2/priority/3",
        "iconUrl": "https://issues.apache.org/jira/images/icons/priorities/major.svg",
        "name": "Major",
        "id": "3"
      },
      "resolution": null,
      "labels": [],
      "attachment": [],
      "issuelinks": [],
      "comment": {
        "comments": [],
        "maxResults": 0,
        "total": 0,
        "startAt": 0
      },
      "votes": {
        "self": "https://issues.apache.org/jira/rest/api/2/issue/YARN-5990/votes",
        "votes": 0,
        "hasVoted": false
      },
      "updated": "2016-12-09T22:25:48.555+0000",
      "status": {
        "self": "https://issues.apache.org/jira/rest/api/2/status/1",
        "description": "The issue is open and ready for the assignee to start work on it.",
        "iconUrl": "https://issues.apache.org/jira/images/icons/statuses/open.png",
        "name": "Open",
        "id": "1",
        "statusCategory": {
          "self": "https://issues.apache.org/jira/rest/api/2/statuscategory/2",
          "id": 2,
          "key": "new",
          "colorName": "blue-gray",
          "name": "To Do"
        }
      }
    }
  },
  "comments_response": {
    "total": 0,
    "comments": [],
    "pages": [
      {
        "url": "https://issues.apache.org/jira/rest/api/2/issue/YARN-5990/comment?startAt=0&maxResults=100",
        "startAt": 0,
        "maxResults": 100,
        "total": 0,
        "returned": 0
      }
    ]
  }
}
